tes3stitch/__init__.py
tes3stitch/__main__.py
tes3stitch/stitch.py
tes3stitch-0.0.2.dist-info/LICENSE
tes3stitch-0.0.2.dist-info/METADATA
tes3stitch-0.0.2.dist-info/WHEEL
tes3stitch-0.0.2.dist-info/entry_points.txt
tes3stitch-0.0.2.dist-info/top_level.txt
tes3stitch-0.0.2.dist-info/RECORD
