Metadata-Version: 2.1
Name: tes3stitch
Version: 0.0.2
Summary: Image stitcher for the TES III: Morrowind CreateMaps command.
Author-email: Kaarel Mänd <kaarel.mand@protonmail.com>
License: MIT License
Project-URL: Homepage, https://github.com/kaarelmand/tes3stitch
Keywords: Morrowind,TES,TES3
Classifier: License :: OSI Approved :: MIT License
Classifier: Programming Language :: Python :: 3
Classifier: Operating System :: OS Independent
License-File: LICENSE
Requires-Dist: Pillow
